[
    {
        "key": "dbln",
        "value": "%7B%2261576435088378%22%3A%226QjbXbxr%22%2C%22100058293865622%22%3A%22gQyhBIIm%22%7D",
        "domain": "facebook.com",
        "path": "/login/device-based/",
        "hostOnly": false,
        "creation": "2025-06-02T00:56:08.610Z",
        "lastAccessed": "2025-06-02T00:56:08.612Z"
    },
    {
        "key": "datr",
        "value": "ymM4aD5uGMh0JhUMZkG4fdjD",
        "domain": "facebook.com",
        "path": "/",
        "hostOnly": false,
        "creation": "2025-06-02T00:56:08.612Z",
        "lastAccessed": "2025-06-02T00:56:08.612Z"
    },
    {
        "key": "sb",
        "value": "ymM4aBrIIaUppiHACClMbTnq",
        "domain": "facebook.com",
        "path": "/",
        "hostOnly": false,
        "creation": "2025-06-02T00:56:08.612Z",
        "lastAccessed": "2025-06-02T00:56:08.612Z"
    },
    {
        "key": "ps_l",
        "value": "1",
        "domain": "facebook.com",
        "path": "/",
        "hostOnly": false,
        "creation": "2025-06-02T00:56:08.612Z",
        "lastAccessed": "2025-06-02T00:56:08.612Z"
    },
    {
        "key": "ps_n",
        "value": "1",
        "domain": "facebook.com",
        "path": "/",
        "hostOnly": false,
        "creation": "2025-06-02T00:56:08.612Z",
        "lastAccessed": "2025-06-02T00:56:08.612Z"
    },
    {
        "key": "vpd",
        "value": "v1%3B583x393x2.75",
        "domain": "facebook.com",
        "path": "/",
        "hostOnly": false,
        "creation": "2025-06-02T00:56:08.612Z",
        "lastAccessed": "2025-06-02T00:56:08.612Z"
    },
    {
        "key": "locale",
        "value": "ar_AR",
        "domain": "facebook.com",
        "path": "/",
        "hostOnly": false,
        "creation": "2025-06-02T00:56:08.612Z",
        "lastAccessed": "2025-06-02T00:56:08.612Z"
    },
    {
        "key": "m_pixel_ratio",
        "value": "2.75",
        "domain": "facebook.com",
        "path": "/",
        "hostOnly": false,
        "creation": "2025-06-02T00:56:08.613Z",
        "lastAccessed": "2025-06-02T00:56:08.613Z"
    },
    {
        "key": "wd",
        "value": "393x699",
        "domain": "facebook.com",
        "path": "/",
        "hostOnly": false,
        "creation": "2025-06-02T00:56:08.613Z",
        "lastAccessed": "2025-06-02T00:56:08.613Z"
    },
    {
        "key": "c_user",
        "value": "100058293865622",
        "domain": "facebook.com",
        "path": "/",
        "hostOnly": false,
        "creation": "2025-06-02T00:56:08.613Z",
        "lastAccessed": "2025-06-02T00:56:08.613Z"
    },
    {
        "key": "xs",
        "value": "18%3A2DKK5Ew-NMTlmA%3A2%3A1748824519%3A-1%3A-1",
        "domain": "facebook.com",
        "path": "/",
        "hostOnly": false,
        "creation": "2025-06-02T00:56:08.613Z",
        "lastAccessed": "2025-06-02T00:56:08.613Z"
    },
    {
        "key": "fr",
        "value": "0Au1n11iow2Br5Y9K.AWeE3_QflTum9iEIhgaG4uoCWyLrHJsGiujItZDzjOsGFnKUX_M.BoOGPK..AAA.0.0.BoPPHQ.AWeSXU6a_Ya2kTuQUQurbQzmYNc",
        "domain": "facebook.com",
        "path": "/",
        "hostOnly": false,
        "creation": "2025-06-02T00:56:08.613Z",
        "lastAccessed": "2025-06-02T00:56:08.613Z"
    },
    {
        "key": "fbl_st",
        "value": "101020916%3BT%3A29147075",
        "domain": "facebook.com",
        "path": "/",
        "hostOnly": false,
        "creation": "2025-06-02T00:56:08.613Z",
        "lastAccessed": "2025-06-02T00:56:08.613Z"
    },
    {
        "key": "wl_cbv",
        "value": "v2%3Bclient_version%3A2834%3Btimestamp%3A1748824528",
        "domain": "facebook.com",
        "path": "/",
        "hostOnly": false,
        "creation": "2025-06-02T00:56:08.613Z",
        "lastAccessed": "2025-06-02T00:56:08.613Z"
    },
    {
        "key": "dpr",
        "value": "2.75",
        "domain": "facebook.com",
        "path": "/",
        "hostOnly": false,
        "creation": "2025-06-02T00:56:08.613Z",
        "lastAccessed": "2025-06-02T00:56:08.613Z"
    }
]
